[
    {
        "id": 4,
        "name": "выпц",
        "description": "ывцырвц",
        "city1": "Генуя",
        "city2": "Болонья",
        "city3": "Рим",
        "date": "2026-05-02 22:39"
    },
    {
        "id": 3,
        "name": "ЫЫ",
        "description": "ЫЫЫ",
        "city1": "Флоренция",
        "city2": "Турин",
        "city3": "Неаполь",
        "date": "2026-04-30 23:31"
    },
    {
        "id": 2,
        "name": "Ненавижу",
        "description": "Кодировку",
        "city1": "Болонья",
        "city2": "Турин",
        "city3": "Пиза",
        "date": "2026-04-30 23:26"
    },
    {
        "id": 1,
        "name": "ТЕСТ",
        "description": "ТЕСТ",
        "city1": "Рим",
        "city2": "Неаполь",
        "city3": "Пиза",
        "date": "2026-04-30 23:21"
    }
]